idfm_api/__init__.py
idfm_api/attribution.py
idfm_api/dataset.py
idfm_api/models.py
idfm_api/utils.py
idfm_api-1.3.1.dist-info/LICENCE
idfm_api-1.3.1.dist-info/METADATA
idfm_api-1.3.1.dist-info/WHEEL
idfm_api-1.3.1.dist-info/top_level.txt
idfm_api-1.3.1.dist-info/RECORD
