Metadata-Version: 2.1
Name: idfm_api
Version: 1.3.1
Summary: API for Ile de france mobilite
Home-page: https://github.com/droso-hass/idfm-api
Author: drosocode
License: MIT
Project-URL: Documentation, https://idfm-api.readthedocs.io/en/latest/
Project-URL: Source, https://github.com/droso-hass/idfm-api
Classifier: Programming Language :: Python :: 3
Classifier: License :: OSI Approved :: MIT License
Classifier: Operating System :: OS Independent
Requires-Python: >=3.7
License-File: LICENCE
Requires-Dist: aiohttp
Requires-Dist: async-timeout
